entitylinking_wikipedia/__init__.py
entitylinking_wikipedia-0.0.8.dist-info/LICENSE
entitylinking_wikipedia-0.0.8.dist-info/METADATA
entitylinking_wikipedia-0.0.8.dist-info/WHEEL
entitylinking_wikipedia-0.0.8.dist-info/top_level.txt
entitylinking_wikipedia-0.0.8.dist-info/RECORD
