Metadata-Version: 2.1
Name: entitylinking-wikipedia
Version: 0.0.8
Summary: Package for Entity Linking using WikiPedia
Home-page: https://github.com/Soumyadipta-Maiti/Package-Creation
Author: Soumyadipta Maiti
Author-email: soumya55555@gmail.com
Keywords: Python,Entity Linking,NER,WikiPedia
Classifier: Development Status :: 1 - Planning
Classifier: Intended Audience :: Developers
Classifier: Programming Language :: Python :: 3
Classifier: Operating System :: Unix
Classifier: Operating System :: MacOS :: MacOS X
Classifier: Operating System :: Microsoft :: Windows
License-File: LICENSE
Requires-Dist: pandas
Requires-Dist: spacy
Requires-Dist: spacy-entity-linker
